dataset_format_benchmark/__init__.py
dataset_format_benchmark/__main__.py
dataset_format_benchmark/matrices.py
dataset_format_benchmark/runner.py
dataset_format_benchmark/datasets/__init__.py
dataset_format_benchmark/datasets/utils.py
dataset_format_benchmark/datasets/kaggle/__init__.py
dataset_format_benchmark/datasets/kaggle/face_masks.py
dataset_format_benchmark/datasets/kaggle/flicrk_image.py
dataset_format_benchmark/datasets/kaggle/wiki_art.py
dataset_format_benchmark/datasets/nvidia/__init__.py
dataset_format_benchmark/datasets/nvidia/downloader.py
dataset_format_benchmark/datasets/nvidia/ffhq.py
dataset_format_benchmark/datasets/own/__init__.py
dataset_format_benchmark/datasets/own/transport.py
dataset_format_benchmark/models/__init__.py
dataset_format_benchmark/models/inception.py
dataset_format_benchmark/storages/__init__.py
dataset_format_benchmark/storages/containers.py
dataset_format_benchmark/storages/fs.py
dataset_format_benchmark-0.2.2.dist-info/AUTHORS.rst
dataset_format_benchmark-0.2.2.dist-info/LICENSE
dataset_format_benchmark-0.2.2.dist-info/METADATA
dataset_format_benchmark-0.2.2.dist-info/WHEEL
dataset_format_benchmark-0.2.2.dist-info/top_level.txt
dataset_format_benchmark-0.2.2.dist-info/RECORD
